kattest/__init__.py
kattest/__main__.py
kattest/data.py
kattest/languages.py
kattest/script.py
kattest-1.2.dist-info/LICENSE
kattest-1.2.dist-info/METADATA
kattest-1.2.dist-info/WHEEL
kattest-1.2.dist-info/entry_points.txt
kattest-1.2.dist-info/top_level.txt
kattest-1.2.dist-info/RECORD
