Metadata-Version: 2.1
Name: kattest
Version: 1.2
Summary: Script for testing your code with the sample data files provided by Kattis, Code Forces and CSES!
Home-page: https://github.com/dilawarm/kattest
Author: Dilawar Mahmood
Author-email: dilawarmm@outlook.com
License: MIT
Download-URL: https://github.com/dilawarm/kattest/archive/v_03.tar.gz
Platform: UNKNOWN
Requires-Dist: emoji
Requires-Dist: beautifulsoup4
